LICENSE.txt
README.md
setup.py
quick_ssh/__init__.py
quick_ssh/app.py
quick_ssh.egg-info/PKG-INFO
quick_ssh.egg-info/SOURCES.txt
quick_ssh.egg-info/dependency_links.txt
quick_ssh.egg-info/entry_points.txt
quick_ssh.egg-info/requires.txt
quick_ssh.egg-info/tmp3vebcups
quick_ssh.egg-info/tmp4zuc2qz1
quick_ssh.egg-info/tmpatb1ifkn
quick_ssh.egg-info/tmpbjdyu2rg
quick_ssh.egg-info/tmpcvlfgtxx
quick_ssh.egg-info/tmpjtmwhk2b
quick_ssh.egg-info/tmpul5tcqjr
quick_ssh.egg-info/tmpvfz7xz3w
quick_ssh.egg-info/top_level.txt
quick_ssh/core/__init__.py
quick_ssh/core/utils.py