Metadata-Version: 2.1
Name: quick-ssh
Version: 0.0.3
Summary: Quick SSH connection manager
Home-page: https://github.com/shivambhilarkar
Author: Shivam Bhilarkar
Author-email: shivambhilarkar@gmail.com
License: MIT
Keywords: quick-ssh,ssh,ssh-manager
License-File: LICENSE.txt
Requires-Dist: prompt-toolkit
Requires-Dist: requests
